semlookp_autocomplete/__init__.py
semlookp_autocomplete/example.py
semlookp_autocomplete/frontend/index.html
semlookp_autocomplete/frontend/main.js
semlookp_autocomplete/frontend/streamlit-component-lib.js
semlookp_autocomplete/frontend/style.css
semlookp_autocomplete/frontend/semlookp-widgets/eui_theme_light.css
semlookp_autocomplete/frontend/semlookp-widgets/manually_maintained_types.d.ts
semlookp_autocomplete/frontend/semlookp-widgets/package.json
semlookp_autocomplete/frontend/semlookp-widgets/semlookp_widgets.js
semlookp_autocomplete/frontend/semlookp-widgets/semlookp_widgets.min.js
streamlit_ontology_elements-0.1.0.dist-info/LICENSE
streamlit_ontology_elements-0.1.0.dist-info/METADATA
streamlit_ontology_elements-0.1.0.dist-info/WHEEL
streamlit_ontology_elements-0.1.0.dist-info/top_level.txt
streamlit_ontology_elements-0.1.0.dist-info/RECORD
