Metadata-Version: 2.1
Name: streamlit-ontology-elements
Version: 0.1.0
Summary: Streamlit component that wraps the ontology elements to query, edit and autocomplete ontology-based terms.
Author: Nils Hoffmann
Author-email: n.hoffmann@fz-juelich.de
Requires-Python: >=3.7
License-File: LICENSE
Requires-Dist: streamlit >=1.2
Requires-Dist: jinja2
